jixer_sync/__init__.py
jixer_sync/base.py
jixer_sync/engines.py
jixer_sync-1.0.1.dist-info/LICENSE
jixer_sync-1.0.1.dist-info/METADATA
jixer_sync-1.0.1.dist-info/WHEEL
jixer_sync-1.0.1.dist-info/top_level.txt
jixer_sync-1.0.1.dist-info/RECORD
