Metadata-Version: 2.1
Name: jixer-sync
Version: 1.0.1
Summary: A Python library for using Search engines.
Home-page: https://github.com/ssb000ss/jixer_sync
Author: ssb000ss
Author-email: ssb000ss@gmail.com
Classifier: Programming Language :: Python :: 3.9
Classifier: License :: OSI Approved :: MIT License
Classifier: Operating System :: OS Independent
License-File: LICENSE
Requires-Dist: requests
